pi7db/__init__.py
pi7db/operators.py
pi7db/cryptopidb/__init__.py
pi7db/filelock/__init__.py
pi7db/filelock/_api.py
pi7db/filelock/_error.py
pi7db/filelock/_soft.py
pi7db/filelock/_unix.py
pi7db/filelock/_util.py
pi7db/filelock/_windows.py
pi7db/filelock/version.py
pi7db/functions/__init__.py
pi7db/functions/functions.py
pi7db/functions/subclass.py
pi7db/status/__init__.py
pi7db-2.1.dist-info/LICENSE
pi7db-2.1.dist-info/METADATA
pi7db-2.1.dist-info/WHEEL
pi7db-2.1.dist-info/top_level.txt
pi7db-2.1.dist-info/RECORD
