Metadata-Version: 2.1
Name: pi7db
Version: 2.1
Summary: pi7db Is A Fast And Powerfull Directory Based Database Built In Python3.
Home-page: https://github.com/shivjeetbhullar/pi7db
Author: Shivjeet Singh Bhullar
Author-email: bhullarshivjeet@gmail.com
License: UNKNOWN
Platform: UNKNOWN
Classifier: Programming Language :: Python :: 3
Classifier: License :: OSI Approved :: GNU General Public License v3 or later (GPLv3+)
Classifier: Operating System :: OS Independent
Classifier: Topic :: Database
Requires-Python: >=3.6
License-File: LICENSE
Requires-Dist: pycryptodome
